pcxarray/__init__.py
pcxarray/cache.py
pcxarray/io.py
pcxarray/processing.py
pcxarray/query.py
pcxarray/utils.py
pcxarray-1.1.1.dist-info/licenses/LICENSE
pcxarray-1.1.1.dist-info/METADATA
pcxarray-1.1.1.dist-info/WHEEL
pcxarray-1.1.1.dist-info/top_level.txt
pcxarray-1.1.1.dist-info/RECORD
