Metadata-Version: 2.4
Name: pcxarray
Version: 1.1.1
Summary: Query and access Microsoft Planetary Computer Data Catalogs using geopandas and xarray.
Author-email: Dakota Hester <dh2306@msstate.edu>, Vitor Souza Martins <vmartins@abe.msstate.edu>
License: MIT License
Project-URL: Homepage, https://github.com/gcermsu/pcxarray
Project-URL: Issues, https://github.com/gcermsu/pcxarray/issues
Requires-Python: >=3.8
License-File: LICENSE
Requires-Dist: requests
Requires-Dist: shapely
Requires-Dist: pystac
Requires-Dist: pystac-client
Requires-Dist: planetary-computer
Requires-Dist: geopandas
Requires-Dist: pyproj
Requires-Dist: rasterio
Requires-Dist: rioxarray
Requires-Dist: tqdm
Requires-Dist: xarray
Requires-Dist: joblib
Requires-Dist: odc-geo
Requires-Dist: bottleneck
Requires-Dist: dask
Provides-Extra: dev
Requires-Dist: build; extra == "dev"
Requires-Dist: twine; extra == "dev"
Requires-Dist: sphinx; extra == "dev"
Requires-Dist: numpydoc; extra == "dev"
Requires-Dist: sphinx-rtd-theme; extra == "dev"
Requires-Dist: nbsphinx; extra == "dev"
Dynamic: license-file
